twg/__init__.py
twg/adapters/base_loader.py
twg/adapters/sqlite_loader.py
twg/adapters/yaml_loader.py
twg/core/cleaner.py
twg/core/config.py
twg/core/db.py
twg/core/model.py
twg/core/schema.sql
twg/ui/app.py
twg/ui/styles.tcss
twg/ui/themes.py
twg/ui/widgets/breadcrumbs.py
twg/ui/widgets/help.py
twg/ui/widgets/inspector.py
twg/ui/widgets/jump.py
twg/ui/widgets/loading.py
twg/ui/widgets/navigator.py
twg/ui/widgets/search.py
twg/ui/widgets/status_bar.py
twg-2.1.4.dist-info/METADATA
twg-2.1.4.dist-info/WHEEL
twg-2.1.4.dist-info/entry_points.txt
twg-2.1.4.dist-info/licenses/LICENSE
twg-2.1.4.dist-info/RECORD
