Metadata-Version: 2.4
Name: twg
Version: 2.1.4
Summary: Terminal-based JSON & YAML viewer (TUI) for exploring and searching large files — fast, interactive, and privacy-first.
Project-URL: Homepage, https://twig.wtf/
Project-URL: Documentation, https://twig.wtf/guide
Project-URL: Repository, https://github.com/workdone0/twig
Project-URL: Issues, https://github.com/workdone0/twig/issues
License-File: LICENSE
Keywords: cli,data-analysis,developer-tools,explorer,json,kubernetes,log-viewer,terminal,tui,viewer,yaml
Classifier: Programming Language :: Python :: 3
Classifier: Programming Language :: Python :: 3.10
Classifier: Programming Language :: Python :: 3.11
Classifier: Programming Language :: Python :: 3.12
Classifier: Programming Language :: Python :: 3.13
Classifier: Programming Language :: Python :: 3.14
Requires-Python: >=3.10
Requires-Dist: ijson>=3.2.0
Requires-Dist: json-repair>=0.30.0
Requires-Dist: pyperclip>=1.8.2
Requires-Dist: pyyaml>=6.0
Requires-Dist: rich>=13.0.0
Requires-Dist: textual>=0.41.0
